pyfolio/__init__.py
pyfolio/_seaborn.py
pyfolio/_version.py
pyfolio/capacity.py
pyfolio/deprecate.py
pyfolio/interesting_periods.py
pyfolio/ipycompat.py
pyfolio/perf_attrib.py
pyfolio/plotting.py
pyfolio/pos.py
pyfolio/round_trips.py
pyfolio/tears.py
pyfolio/timeseries.py
pyfolio/txn.py
pyfolio/utils.py
pyfolio/tests/__init__.py
pyfolio/tests/test_capacity.py
pyfolio/tests/test_nbs.py
pyfolio/tests/test_perf_attrib.py
pyfolio/tests/test_pos.py
pyfolio/tests/test_round_trips.py
pyfolio/tests/test_tears.py
pyfolio/tests/test_timeseries.py
pyfolio/tests/test_txn.py
pyfolio_qa-0.0.1.dist-info/LICENSE
pyfolio_qa-0.0.1.dist-info/METADATA
pyfolio_qa-0.0.1.dist-info/WHEEL
pyfolio_qa-0.0.1.dist-info/top_level.txt
pyfolio_qa-0.0.1.dist-info/RECORD
